[
  {
    "time": "2026-05-14T10:06:58.377Z",
    "action": "app-started",
    "detail": "应用启动"
  },
  {
    "time": "2026-05-14T10:15:12.435Z",
    "action": "product-saved",
    "detail": "#17184 16图 ¥109"
  },
  {
    "time": "2026-05-14T10:16:04.349Z",
    "action": "export",
    "detail": "导出 1 个商品到 C:\\Users\\qingf\\Desktop\\shop\\exports\\products_2026-05-14T10-16-03.xlsx"
  },
  {
    "time": "2026-05-14T10:19:27.673Z",
    "action": "app-started",
    "detail": "应用启动"
  },
  {
    "time": "2026-05-14T10:27:33.209Z",
    "action": "app-started",
    "detail": "应用启动"
  },
  {
    "time": "2026-05-14T10:28:14.987Z",
    "action": "product-saved",
    "detail": "#17184 16图 ¥109"
  },
  {
    "time": "2026-05-14T10:29:29.063Z",
    "action": "export",
    "detail": "导出 1 个商品到 C:\\Users\\qingf\\Desktop\\shop\\exports\\products_2026-05-14T10-29-28.xlsx"
  },
  {
    "time": "2026-05-14T10:30:34.413Z",
    "action": "product-saved",
    "detail": "#17184 16图 ¥109"
  },
  {
    "time": "2026-05-14T10:31:33.676Z",
    "action": "export",
    "detail": "导出 1 个商品到 C:\\Users\\qingf\\Desktop\\shop\\exports\\products_2026-05-14T10-31-33.xlsx"
  },
  {
    "time": "2026-05-14T10:34:34.258Z",
    "action": "app-started",
    "detail": "应用启动"
  },
  {
    "time": "2026-05-14T10:37:18.593Z",
    "action": "app-started",
    "detail": "应用启动"
  },
  {
    "time": "2026-05-14T10:37:54.787Z",
    "action": "product-saved",
    "detail": "#17184 16图 ¥109"
  },
  {
    "time": "2026-05-14T10:41:34.220Z",
    "action": "app-started",
    "detail": "应用启动"
  },
  {
    "time": "2026-05-14T10:42:16.204Z",
    "action": "product-saved",
    "detail": "#17184 16图 ¥109"
  },
  {
    "time": "2026-05-14T10:46:56.865Z",
    "action": "app-started",
    "detail": "应用启动"
  },
  {
    "time": "2026-05-14T10:50:20.464Z",
    "action": "app-started",
    "detail": "应用启动"
  },
  {
    "time": "2026-05-14T10:51:49.465Z",
    "action": "export",
    "detail": "导出 1 个商品到 C:\\Users\\qingf\\Desktop\\shop\\exports\\products_2026-05-14T10-51-49.xlsx"
  },
  {
    "time": "2026-05-14T10:52:35.116Z",
    "action": "product-saved",
    "detail": "#17184 16图 ¥109"
  },
  {
    "time": "2026-05-14T10:52:41.405Z",
    "action": "product-saved",
    "detail": "#17084 21图 ¥219"
  },
  {
    "time": "2026-05-14T10:52:48.893Z",
    "action": "product-saved",
    "detail": "#16975 19图 ¥279"
  },
  {
    "time": "2026-05-14T10:53:00.310Z",
    "action": "product-saved",
    "detail": "#17097 20图 ¥209"
  },
  {
    "time": "2026-05-14T10:53:05.718Z",
    "action": "product-saved",
    "detail": "#17122 16图 ¥239"
  },
  {
    "time": "2026-05-14T10:53:10.860Z",
    "action": "product-saved",
    "detail": "#16972 23图 ¥319"
  },
  {
    "time": "2026-05-14T10:53:17.918Z",
    "action": "product-saved",
    "detail": "#17076 20图 ¥"
  },
  {
    "time": "2026-05-14T10:53:27.737Z",
    "action": "product-saved",
    "detail": "#16996 16图 ¥139"
  },
  {
    "time": "2026-05-14T10:53:34.036Z",
    "action": "product-saved",
    "detail": "#16745 19图 ¥229"
  },
  {
    "time": "2026-05-14T10:53:42.292Z",
    "action": "product-saved",
    "detail": "#16996 20图 ¥139"
  },
  {
    "time": "2026-05-14T10:53:48.055Z",
    "action": "product-saved",
    "detail": "#16985 17图 ¥339"
  },
  {
    "time": "2026-05-14T10:53:52.721Z",
    "action": "product-saved",
    "detail": "#17044 17图 ¥149"
  },
  {
    "time": "2026-05-14T10:54:06.195Z",
    "action": "product-saved",
    "detail": "#17100 16图 ¥"
  },
  {
    "time": "2026-05-14T10:54:10.557Z",
    "action": "product-saved",
    "detail": "#15076 17图 ¥"
  },
  {
    "time": "2026-05-14T10:54:16.436Z",
    "action": "product-saved",
    "detail": "#16980 16图 ¥"
  },
  {
    "time": "2026-05-14T10:54:26.293Z",
    "action": "product-saved",
    "detail": "#16973 18图 ¥"
  },
  {
    "time": "2026-05-14T10:54:35.920Z",
    "action": "product-saved",
    "detail": "#16999 31图 ¥"
  },
  {
    "time": "2026-05-14T10:54:41.206Z",
    "action": "product-saved",
    "detail": "#16988 26图 ¥"
  },
  {
    "time": "2026-05-14T10:54:47.399Z",
    "action": "product-saved",
    "detail": "#16973 23图 ¥"
  },
  {
    "time": "2026-05-14T10:54:53.710Z",
    "action": "product-saved",
    "detail": "#17100 21图 ¥"
  },
  {
    "time": "2026-05-14T11:02:48.395Z",
    "action": "export",
    "detail": "导出 20 个商品到 C:\\Users\\qingf\\Desktop\\shop\\exports\\products_2026-05-14T11-02-47.xlsx"
  },
  {
    "time": "2026-05-14T11:04:22.884Z",
    "action": "app-started",
    "detail": "应用启动"
  },
  {
    "time": "2026-05-14T11:05:13.102Z",
    "action": "product-saved",
    "detail": "#17184 33图 ¥109"
  },
  {
    "time": "2026-05-14T11:05:16.299Z",
    "action": "product-saved",
    "detail": "#17084 23图 ¥219"
  },
  {
    "time": "2026-05-14T11:27:57.177Z",
    "action": "app-started",
    "detail": "应用启动"
  },
  {
    "time": "2026-05-14T12:01:30.348Z",
    "action": "export",
    "detail": "导出 2 个商品到 C:\\Users\\qingf\\Desktop\\shop\\exports\\products_2026-05-14T12-01-29.xlsx"
  },
  {
    "time": "2026-05-14T12:04:32.449Z",
    "action": "app-started",
    "detail": "应用启动"
  }
]